fredapi/__init__.py
fredapi/fred.py
fredapi/version.py
fredapi-0.5.1.dist-info/LICENSE
fredapi-0.5.1.dist-info/METADATA
fredapi-0.5.1.dist-info/WHEEL
fredapi-0.5.1.dist-info/top_level.txt
fredapi-0.5.1.dist-info/RECORD
